odoo/addons/account_invoice_update_check/README.rst
odoo/addons/account_invoice_update_check/__init__.py
odoo/addons/account_invoice_update_check/__manifest__.py
odoo/addons/account_invoice_update_check/i18n/fr.po
odoo/addons/account_invoice_update_check/models/__init__.py
odoo/addons/account_invoice_update_check/models/account_invoice_line.py
odoo/addons/account_invoice_update_check/readme/CONTRIBUTORS.rst
odoo/addons/account_invoice_update_check/readme/DESCRIPTION.rst
odoo/addons/account_invoice_update_check/static/description/icon.png
odoo/addons/account_invoice_update_check/static/description/index.html
odoo/addons/account_invoice_update_check/tests/__init__.py
odoo/addons/account_invoice_update_check/tests/test_module.py
odoo12_addon_account_invoice_update_check-12.0.1.0.2.dist-info/METADATA
odoo12_addon_account_invoice_update_check-12.0.1.0.2.dist-info/WHEEL
odoo12_addon_account_invoice_update_check-12.0.1.0.2.dist-info/top_level.txt
odoo12_addon_account_invoice_update_check-12.0.1.0.2.dist-info/RECORD
